umakaparser/__init__.py
umakaparser/locales/cmd.en.json
umakaparser/locales/cmd.ja.json
umakaparser/scripts/__init__.py
umakaparser/scripts/services/__init__.py
umakaparser/scripts/services/assets.py
umakaparser/scripts/services/build.py
umakaparser/scripts/services/convert.py
umakaparser/scripts/services/utils.py
umakaparser/scripts/services/validate.py
umakaparser/services.py
umakaparser-0.2.3.dist-info/METADATA
umakaparser-0.2.3.dist-info/WHEEL
umakaparser-0.2.3.dist-info/entry_points.txt
umakaparser-0.2.3.dist-info/RECORD
